soumi/__init__.py
soumi/soumifirst.py
soumi-1.1.1.dist-info/LICENSE.txt
soumi-1.1.1.dist-info/METADATA
soumi-1.1.1.dist-info/WHEEL
soumi-1.1.1.dist-info/top_level.txt
soumi-1.1.1.dist-info/RECORD
