Metadata-Version: 2.1
Name: soumi
Version: 1.1.1
Summary: A small package to help with simple mathematical operations
Home-page: https://github.com/Soumitra-Mandal/python-packaging
Author: Soumitra Mandal
Author-email: soumitramandal1999@gmail.com
License: UNKNOWN
Platform: UNKNOWN
Classifier: Programming Language :: Python :: 3
Classifier: License :: OSI Approved :: MIT License
Classifier: Operating System :: OS Independent
License-File: LICENSE.txt
Requires-Dist: matplotlib
